haystack_bm25/__init__.py
haystack_bm25/rank_bm25.py
haystack_bm25-1.0.1.dist-info/METADATA
haystack_bm25-1.0.1.dist-info/WHEEL
haystack_bm25-1.0.1.dist-info/licenses/LICENSE
haystack_bm25-1.0.1.dist-info/RECORD
