Metadata-Version: 2.1
Name: haystack-bm25
Version: 1.0.1
Summary: Various BM25 algorithms for document ranking
Project-URL: Homepage, https://github.com/deepset-ai/haystack-bm25
Author-email: "D. Brown" <dorianstuartbrown@gmail.com>
License-Expression: Apache-2.0
License-File: LICENSE
Classifier: Development Status :: 5 - Production/Stable
Classifier: Intended Audience :: Science/Research
Classifier: License :: Freely Distributable
Classifier: License :: OSI Approved :: Apache Software License
Classifier: Operating System :: OS Independent
Classifier: Programming Language :: Python
Classifier: Programming Language :: Python :: 3
Classifier: Programming Language :: Python :: 3.8
Classifier: Programming Language :: Python :: 3.9
Classifier: Programming Language :: Python :: 3.10
Requires-Dist: numpy
